tfdpython/__init__.py
tfdpython/tinyfiledialogs64.dll
tfdpython/tinyfiledialogsAppleSilicon.dylib
tfdpython/tinyfiledialogsLinux86.so
tfdpython-2025.0.0.dist-info/METADATA
tfdpython-2025.0.0.dist-info/WHEEL
tfdpython-2025.0.0.dist-info/licenses/LICENSE
tfdpython-2025.0.0.dist-info/RECORD
