Metadata-Version: 2.4
Name: tfdpython
Version: 2025.0.0
Summary: Python wrapper for tinyfiledialogs.
Author-email: Annes <anneswidow@gmail.com>
Maintainer-email: Annes <anneswidow@gmail.com>
License-Expression: MIT
License-File: LICENSE
Keywords: annes,tinyfiledialogs,wrapper
Classifier: Development Status :: 4 - Beta
Classifier: Programming Language :: Python
Requires-Python: >=3.8
